trove/__init__.py
trove/archive.py
trove/build.py
trove/clean.py
trove/collate.py
trove/config_parser.py
trove/evaluate.py
trove/execute.py
trove/management.py
treasure_trove-0.1.dist-info/METADATA
treasure_trove-0.1.dist-info/WHEEL
treasure_trove-0.1.dist-info/top_level.txt
treasure_trove-0.1.dist-info/RECORD
